nonebot_plugin_osu_match_monitor/__init__.py
nonebot_plugin_osu_match_monitor/config.py
nonebot_plugin_osu_match_monitor-1.2.4.dist-info/LICENSE
nonebot_plugin_osu_match_monitor-1.2.4.dist-info/METADATA
nonebot_plugin_osu_match_monitor-1.2.4.dist-info/WHEEL
nonebot_plugin_osu_match_monitor-1.2.4.dist-info/top_level.txt
nonebot_plugin_osu_match_monitor-1.2.4.dist-info/RECORD
