Metadata-Version: 2.1
Name: nonebot-plugin-osu-match-monitor
Version: 1.2.4
Summary: 一个监控osu!多人游戏房间动态的插件
Author-email: Sevenyine <tntobsidian@126.com>
License: GNU GENERAL PUBLIC LICENSE
Project-URL: Homepage, https://github.com/Sevenyine/nonebot-plugin-osu-match-monitor
Project-URL: Documentation, https://github.com/Sevenyine/nonebot-plugin-osu-match-monitor/blob/master/README.md
Project-URL: Source, https://github.com/Sevenyine/nonebot-plugin-osu-match-monitor
Project-URL: Tracker, https://github.com/Sevenyine/nonebot-plugin-osu-match-monitor/issues
Keywords: nonebot2,osu!,osu
Classifier: Framework :: AsyncIO
Classifier: License :: OSI Approved :: GNU General Public License v3 (GPLv3)
Classifier: Operating System :: OS Independent
Classifier: Programming Language :: Python
Classifier: Programming Language :: Python :: 3
Classifier: Programming Language :: Python :: 3.9
Classifier: Programming Language :: Python :: 3.10
Classifier: Programming Language :: Python :: 3.11
License-File: LICENSE
Requires-Dist: nonebot2>=2.2.0
Requires-Dist: nonebot-adapter-onebot>=2.0.0
Requires-Dist: httpx>=0.23.0
